LICENSE.txt
MANIFEST.in
README.md
setup.py
OkCat.egg-info/PKG-INFO
OkCat.egg-info/SOURCES.txt
OkCat.egg-info/dependency_links.txt
OkCat.egg-info/entry_points.txt
OkCat.egg-info/requires.txt
OkCat.egg-info/top_level.txt
okcat/__init__.py
okcat/adb.py
okcat/confloader.py
okcat/helper.py
okcat/logfile_parser.py
okcat/logprocessor.py
okcat/logregex.py
okcat/logseparator.py
okcat/terminalcolor.py
okcat/trans.py