Metadata-Version: 1.1
Name: OkCat
Version: 1.1.3
Summary: An powerful log processor
Home-page: https://github.com/Jacksgong/okcat
Author: Jacksgong
Author-email: igzhenjie@gmail.com
License: Apache2
Keywords: okcat log 'log processor' 'log filter'
Platform: UNKNOWN
Classifier: Development Status :: 5 - Production/Stable
Classifier: License :: OSI Approved :: Apache Software License
Classifier: Programming Language :: Python :: 2.7
Classifier: Programming Language :: Python :: 3
Classifier: Programming Language :: Python :: 3.3
Classifier: Programming Language :: Python :: 3.4
Classifier: Programming Language :: Python :: 3.5
Classifier: Programming Language :: Python :: 3.6
